[{"analyze_labels": [{"segment_labels_data": [{"segment_labels_description": "font", "category_entity_data": [{"description": "software"}]}, {"segment_labels_description": "logo", "category_entity_data": [{"description": "graphics"}]}, {"segment_labels_description": "text", "category_entity_data": []}, {"segment_labels_description": "graphic design", "category_entity_data": [{"description": "artwork"}]}, {"segment_labels_description": "brand", "category_entity_data": []}, {"segment_labels_description": "valentine's day", "category_entity_data": [{"description": "holiday"}]}, {"segment_labels_description": "graphics", "category_entity_data": [{"description": "artwork"}]}, {"segment_labels_description": "love", "category_entity_data": [{"description": "person"}]}, {"segment_labels_description": "heart", "category_entity_data": []}], "shot_label_data": [{"shot_label_description": "white", "category_entity_data": []}, {"shot_label_description": "heart", "category_entity_data": [{"description": "organ"}]}, {"shot_label_description": "text", "category_entity_data": []}, {"shot_label_description": "graphic design", "category_entity_data": [{"description": "artwork"}]}, {"shot_label_description": "valentine's day", "category_entity_data": [{"description": "holiday"}]}, {"shot_label_description": "brand", "category_entity_data": []}, {"shot_label_description": "song", "category_entity_data": [{"description": "music"}]}, {"shot_label_description": "black and white", "category_entity_data": [{"description": "style"}]}, {"shot_label_description": "logo", "category_entity_data": [{"description": "graphics"}]}, {"shot_label_description": "love", "category_entity_data": [{"description": "person"}]}, {"shot_label_description": "heart", "category_entity_data": []}, {"shot_label_description": "clip art", "category_entity_data": [{"description": "graphics"}]}, {"shot_label_description": "graphics", "category_entity_data": [{"description": "artwork"}]}, {"shot_label_description": "lyrics", "category_entity_data": []}, {"shot_label_description": "font", "category_entity_data": [{"description": "software"}]}], "frame_labels_data": [{"frame_label_description": "pattern", "category_entity_data": [{"description": "design"}]}, {"frame_label_description": "black", "category_entity_data": []}, {"frame_label_description": "text", "category_entity_data": []}, {"frame_label_description": "computer wallpaper", "category_entity_data": [{"description": "software"}]}, {"frame_label_description": "product design", "category_entity_data": [{"description": "person"}]}, {"frame_label_description": "monochrome photography", "category_entity_data": [{"description": "photography"}]}, {"frame_label_description": "joint", "category_entity_data": [{"description": "human body"}]}, {"frame_label_description": "signage", "category_entity_data": []}, {"frame_label_description": "angle", "category_entity_data": []}, {"frame_label_description": "square", "category_entity_data": [{"description": "shape"}]}, {"frame_label_description": "smile", "category_entity_data": [{"description": "person"}]}, {"frame_label_description": "peach", "category_entity_data": []}, {"frame_label_description": "document", "category_entity_data": [{"description": "paper"}]}, {"frame_label_description": "area", "category_entity_data": []}, {"frame_label_description": "circle", "category_entity_data": [{"description": "shape"}]}, {"frame_label_description": "magenta", "category_entity_data": []}, {"frame_label_description": "diagram", "category_entity_data": []}, {"frame_label_description": "material property", "category_entity_data": [{"description": "material"}]}, {"frame_label_description": "heart", "category_entity_data": []}, {"frame_label_description": "number", "category_entity_data": [{"description": "symbol"}]}, {"frame_label_description": "love", "category_entity_data": [{"description": "person"}]}, {"frame_label_description": "line", "category_entity_data": [{"description": "shape"}]}, {"frame_label_description": "writing", "category_entity_data": []}, {"frame_label_description": "clip art", "category_entity_data": [{"description": "graphics"}]}, {"frame_label_description": "brand", "category_entity_data": []}, {"frame_label_description": "graphic design", "category_entity_data": [{"description": "artwork"}]}, {"frame_label_description": "valentine's day", "category_entity_data": [{"description": "holiday"}]}, {"frame_label_description": "logo", "category_entity_data": [{"description": "graphics"}]}, {"frame_label_description": "trademark", "category_entity_data": []}, {"frame_label_description": "calligraphy", "category_entity_data": [{"description": "artwork"}, {"description": "art"}]}, {"frame_label_description": "black and white", "category_entity_data": [{"description": "style"}]}, {"frame_label_description": "product", "category_entity_data": [{"description": "person"}]}, {"frame_label_description": "mouth", "category_entity_data": []}, {"frame_label_description": "heart", "category_entity_data": [{"description": "organ"}]}, {"frame_label_description": "advertising", "category_entity_data": []}, {"frame_label_description": "petal", "category_entity_data": []}, {"frame_label_description": "white", "category_entity_data": []}, {"frame_label_description": "paper", "category_entity_data": [{"description": "material"}]}, {"frame_label_description": "symbol", "category_entity_data": [{"description": "information"}]}, {"frame_label_description": "design", "category_entity_data": []}, {"frame_label_description": "event", "category_entity_data": []}, {"frame_label_description": "organ", "category_entity_data": [{"description": "human body"}]}, {"frame_label_description": "banner", "category_entity_data": [{"description": "advertising"}]}, {"frame_label_description": "font", "category_entity_data": [{"description": "software"}]}, {"frame_label_description": "monochrome", "category_entity_data": [{"description": "style"}]}, {"frame_label_description": "illustration", "category_entity_data": [{"description": "art"}]}, {"frame_label_description": "shoe", "category_entity_data": []}, {"frame_label_description": "rectangle", "category_entity_data": [{"description": "shape"}]}, {"frame_label_description": "graphics", "category_entity_data": [{"description": "artwork"}]}, {"frame_label_description": "product", "category_entity_data": []}]}], "speech_transcription": [], "video_detect_text": [{"text": "Peof", "confidence": 0.8941822052001953}, {"text": "You", "confidence": 0.9170739054679871}, {"text": "WC", "confidence": 0.8541613817214966}, {"text": "Peot", "confidence": 0.7408522367477417}, {"text": "M", "confidence": 0.9322881698608398}, {"text": "W", "confidence": 0.8031998872756958}], "track_objects": []}]